nxsconfigserver/ComponentParser.py
nxsconfigserver/Errors.py
nxsconfigserver/MYSQLDataBase.py
nxsconfigserver/Merger.py
nxsconfigserver/NXSConfigServer.py
nxsconfigserver/Release.py
nxsconfigserver/StreamSet.py
nxsconfigserver/XMLConfigurator.py
nxsconfigserver/__init__.py
nxsconfigserver-2.21.2.data/scripts/NXSConfigServer
nxsconfigserver-2.21.2.dist-info/METADATA
nxsconfigserver-2.21.2.dist-info/WHEEL
nxsconfigserver-2.21.2.dist-info/top_level.txt
nxsconfigserver-2.21.2.dist-info/RECORD
