Metadata-Version: 2.1
Name: nxsconfigserver
Version: 2.21.2
Summary: Configuration Server for Nexus Data Writer
Home-page: http://github.com/jkotan/nexdatas/nxsconfigserver
Author: Jan Kotanski, Eugen Wintersberger , Halil Pasic
Author-email: jankotan@gmail.com, eugen.wintersberger@gmail.com, halil.pasic@gmail.com
License: GNU GENERAL PUBLIC LICENSE v3
Keywords: configuration MySQL writer Tango server nexus data
Classifier: Development Status :: 5 - Production/Stable
Classifier: Intended Audience :: Science/Research
Classifier: Topic :: Scientific/Engineering :: Physics
Classifier: Topic :: Software Development :: Libraries :: Python Modules
Classifier: License :: OSI Approved :: GNU General Public License v3 (GPLv3)
Classifier: Programming Language :: Python :: 2.7
Classifier: Programming Language :: Python :: 3
Classifier: Programming Language :: Python :: 3.4
Classifier: Programming Language :: Python :: 3.5
Classifier: Programming Language :: Python :: 3.6
Classifier: Programming Language :: Python :: 3.7
Classifier: Programming Language :: Python :: 3.8
Classifier: Programming Language :: Python :: 3.9
Classifier: Programming Language :: Python :: 3.10
Classifier: Programming Language :: Python :: 3.11
Classifier: Programming Language :: Python :: 3.12
Classifier: Programming Language :: Python :: 3.13
Requires-Dist: lxml
